promptdesk/JSONMapper.py
promptdesk/__init__.py
promptdesk/chain.py
promptdesk/client.py
promptdesk-0.2.7.dist-info/LICENSE
promptdesk-0.2.7.dist-info/METADATA
promptdesk-0.2.7.dist-info/WHEEL
promptdesk-0.2.7.dist-info/RECORD
