Metadata-Version: 2.1
Name: promptdesk
Version: 0.2.7
Summary: PromptDesk python SDK.
Home-page: https://promptdesk.ai/
License: MIT
Author: PromptDesk
Author-email: feedback@promptdesk.ai
Requires-Python: >=3.8,<4.0
Classifier: License :: OSI Approved :: MIT License
Classifier: Programming Language :: Python :: 3
Classifier: Programming Language :: Python :: 3.8
Classifier: Programming Language :: Python :: 3.9
Classifier: Programming Language :: Python :: 3.10
Classifier: Programming Language :: Python :: 3.11
Requires-Dist: cachetools (>=5.3.2,<6.0.0)
Requires-Dist: pybars3 (>=0.9.7,<0.10.0)
Requires-Dist: python-dotenv (>=1.0.0,<2.0.0)
Requires-Dist: requests (>=2.31.0,<3.0.0)
Project-URL: Documentation, https://promptdesk.ai/docs
Project-URL: Repository, https://github.com/promptdesk/promptdesk-py
